create_app/__init__.py
create_app/apps.py
create_app/management/__init__.py
create_app/management/commands/__init__.py
create_app/management/commands/startapp.py
django_create_app-1.0.1.dist-info/METADATA
django_create_app-1.0.1.dist-info/WHEEL
django_create_app-1.0.1.dist-info/top_level.txt
django_create_app-1.0.1.dist-info/RECORD
