Metadata-Version: 2.1
Name: django-create-app
Version: 1.0.1
Summary: A Django app (custom) that modifies the startapp command to ensure all apps are created inside a directory defined by DEFAULT_APPS_DIR in settings.py.
Home-page: https://github.com/sachin-acharya-projects/django-create-app
Author: Sachin Acharya
License: MIT License
Keywords: django-create-app django-app django-startapp
Classifier: Framework :: Django
Classifier: Intended Audience :: Developers
Classifier: License :: OSI Approved :: MIT License
Classifier: Operating System :: OS Independent
Classifier: Programming Language :: Python
Classifier: Programming Language :: Python :: 3
Classifier: Programming Language :: Python :: 3.8
Requires-Python: >=3.8
Requires-Dist: Django >=3.2
